flet_contrib/color_picker/README.md
flet_contrib/color_picker/__init__.py
flet_contrib/color_picker/examples/color_picker_dialog.py
flet_contrib/color_picker/examples/color_picker_dialog_async.py
flet_contrib/color_picker/examples/hue_slider_example.py
flet_contrib/color_picker/examples/update_color_property.py
flet_contrib/color_picker/media/color_picker.png
flet_contrib/color_picker/src/color_picker.py
flet_contrib/color_picker/src/hue_slider.py
flet_contrib/color_picker/src/palette_color_picker.py
flet_contrib/color_picker/src/utils.py
flet_contrib/flexible_slider/README.md
flet_contrib/flexible_slider/__init__.py
flet_contrib/flexible_slider/examples/horizontal_slider_example.py
flet_contrib/flexible_slider/examples/vertical_slider_example.py
flet_contrib/flexible_slider/src/flexible_slider.py
flet_contrib/shimmer/README.md
flet_contrib/shimmer/__init__.py
flet_contrib/shimmer/examples/shimmer_async_common_shimmer.py
flet_contrib/shimmer/examples/shimmer_async_individual_ctrl_effect.py
flet_contrib/shimmer/examples/shimmer_sync_mode_common_effect.py
flet_contrib/shimmer/media/shimmer_common_async.mp4
flet_contrib/shimmer/src/shimmer.py
flet_contrib/vertical_splitter/README.md
flet_contrib/vertical_splitter/__init__.py
flet_contrib/vertical_splitter/examples/vertical_splitter_with_containers.py
flet_contrib/vertical_splitter/examples/vertical_splitter_with_navigationrail_and_text.py
flet_contrib/vertical_splitter/src/vertical_splitter.py
flet_contrib-2024.1.24.dist-info/LICENSE
flet_contrib-2024.1.24.dist-info/METADATA
flet_contrib-2024.1.24.dist-info/WHEEL
flet_contrib-2024.1.24.dist-info/RECORD
